trolley/__init__.py
trolley/balances_gateway.py
trolley/batch_gateway.py
trolley/client.py
trolley/configuration.py
trolley/gateway.py
trolley/invoice_gateway.py
trolley/invoice_line_gateway.py
trolley/invoice_payment_gateway.py
trolley/offline_payment_gateway.py
trolley/payment_gateway.py
trolley/recipient_account_gateway.py
trolley/recipient_gateway.py
trolley/exceptions/__init__.py
trolley/exceptions/authenticationException.py
trolley/exceptions/authorizationException.py
trolley/exceptions/baseException.py
trolley/exceptions/downForMaintenanceException.py
trolley/exceptions/invalidFieldException.py
trolley/exceptions/invalidServerConnectionException.py
trolley/exceptions/invalidStatusException.py
trolley/exceptions/malformedException.py
trolley/exceptions/notFoundException.py
trolley/exceptions/tooManyRequestsException.py
trolley/exceptions/unexpectedException.py
trolley/types/balances.py
trolley/types/batch.py
trolley/types/batch_summary.py
trolley/types/invoice.py
trolley/types/invoice_line.py
trolley/types/invoice_payment.py
trolley/types/invoice_payment_part.py
trolley/types/log.py
trolley/types/meta.py
trolley/types/offline_payment.py
trolley/types/payment.py
trolley/types/recipient.py
trolley/types/recipient_account.py
trolley/utils/url_utils.py
trolleyhq-1.0.1.dist-info/LICENSE
trolleyhq-1.0.1.dist-info/METADATA
trolleyhq-1.0.1.dist-info/WHEEL
trolleyhq-1.0.1.dist-info/top_level.txt
trolleyhq-1.0.1.dist-info/RECORD
