Metadata-Version: 2.1
Name: trolleyhq
Version: 1.0.1
Home-page: https://www.trolley.com
Author: Trolley
Author-email: developer-tools@trolley.com
License: MIT
License-File: LICENSE
Requires-Dist: requests >=2.31.0
